<annotation>
  <folder>GTSDB</folder>
  <filename>20180704___alizan___0135_136.jpg</filename>
  <size>
    <width>180</width>
    <height>320</height>
    <depth>3</depth>
  </size>
  <object>
    <name>hand</name>
    <flag>1</flag>
    <difficult>0</difficult>
    <bndbox>
      <xmin>96</xmin>
      <ymin>157</ymin>
      <xmax>106</xmax>
      <ymax>180</ymax>
    </bndbox>
  </object>
  <object>
    <name>hand</name>
    <flag>1</flag>
    <difficult>0</difficult>
    <bndbox>
      <xmin>95</xmin>
      <ymin>114</ymin>
      <xmax>111</xmax>
      <ymax>145</ymax>
    </bndbox>
  </object>
</annotation>